AioZohoSDPlusAPI/__init__.py
AioZohoSDPlusAPI/admin.py
AioZohoSDPlusAPI/announcements.py
AioZohoSDPlusAPI/approvals.py
AioZohoSDPlusAPI/asset.py
AioZohoSDPlusAPI/change.py
AioZohoSDPlusAPI/cmdb.py
AioZohoSDPlusAPI/comments.py
AioZohoSDPlusAPI/contract.py
AioZohoSDPlusAPI/device_registration.py
AioZohoSDPlusAPI/personalization.py
AioZohoSDPlusAPI/problem.py
AioZohoSDPlusAPI/project.py
AioZohoSDPlusAPI/purchase_order.py
AioZohoSDPlusAPI/release.py
AioZohoSDPlusAPI/report.py
AioZohoSDPlusAPI/request.py
AioZohoSDPlusAPI/sdp_aio_api_core.py
AioZohoSDPlusAPI/solutions.py
AioZohoSDPlusAPI/space.py
AioZohoSDPlusAPI/task.py
AioZohoSDPlusAPI/worklog.py
AioZohoSDPlusAPI-0.0.4.dist-info/METADATA
AioZohoSDPlusAPI-0.0.4.dist-info/WHEEL
AioZohoSDPlusAPI-0.0.4.dist-info/top_level.txt
AioZohoSDPlusAPI-0.0.4.dist-info/RECORD
